<?xml version="1.0" encoding="UTF-8" ?>
<FEEDBACK VERSION="200701" COMMENT="XML-Importfile for mod/feedback">
     <ITEMS>
          <ITEM TYPE="label" REQUIRED="0">
               <ITEMID><![CDATA[1000]]></ITEMID>
               <ITEMTEXT><![CDATA[]]></ITEMTEXT>
               <ITEMLABEL><![CDATA[]]></ITEMLABEL>
               <PRESENTATION><![CDATA[<h4>グループ2, 10:00--10:10 (和田　親宗)</h4>]]></PRESENTATION>
               <OPTIONS><![CDATA[]]></OPTIONS>
               <DEPENDITEM><![CDATA[0]]></DEPENDITEM>
               <DEPENDVALUE><![CDATA[]]></DEPENDVALUE>
          </ITEM>
          <ITEM TYPE="label" REQUIRED="0">
               <ITEMID><![CDATA[1001]]></ITEMID>
               <ITEMTEXT><![CDATA[]]></ITEMTEXT>
               <ITEMLABEL><![CDATA[]]></ITEMLABEL>
               <PRESENTATION><![CDATA[<p><strong><span style="color: #ff0000;">評価値　　A: 100点、B:90点、C:80点、D:70点、E:60点、X:0点</span></strong></p>]]></PRESENTATION>
               <OPTIONS><![CDATA[]]></OPTIONS>
               <DEPENDITEM><![CDATA[0]]></DEPENDITEM>
               <DEPENDVALUE><![CDATA[]]></DEPENDVALUE>
          </ITEM>
          <ITEM TYPE="label" REQUIRED="0">
               <ITEMID><![CDATA[1002]]></ITEMID>
               <ITEMTEXT><![CDATA[]]></ITEMTEXT>
               <ITEMLABEL><![CDATA[]]></ITEMLABEL>
               <PRESENTATION><![CDATA[<h5>22221203&nbsp; &nbsp;酒井　日菜実</h5>]]></PRESENTATION>
               <OPTIONS><![CDATA[]]></OPTIONS>
               <DEPENDITEM><![CDATA[0]]></DEPENDITEM>
               <DEPENDVALUE><![CDATA[]]></DEPENDVALUE>
          </ITEM>
          <ITEM TYPE="multichoice" REQUIRED="0">
               <ITEMID><![CDATA[1003]]></ITEMID>
               <ITEMTEXT><![CDATA[この学生の指導教員です]]></ITEMTEXT>
               <ITEMLABEL><![CDATA[22221203-0]]></ITEMLABEL>
               <PRESENTATION><![CDATA[c>>>>>YES<<<<<1]]></PRESENTATION>
               <OPTIONS><![CDATA[h]]></OPTIONS>
               <DEPENDITEM><![CDATA[0]]></DEPENDITEM>
               <DEPENDVALUE><![CDATA[]]></DEPENDVALUE>
          </ITEM>
          <ITEM TYPE="multichoice" REQUIRED="0">
               <ITEMID><![CDATA[1004]]></ITEMID>
               <ITEMTEXT><![CDATA[1. 研究成果]]></ITEMTEXT>
               <ITEMLABEL><![CDATA[22221203-1]]></ITEMLABEL>
               <PRESENTATION><![CDATA[r>>>>>A|B|C|D|E|X<<<<<1]]></PRESENTATION>
               <OPTIONS><![CDATA[h]]></OPTIONS>
               <DEPENDITEM><![CDATA[0]]></DEPENDITEM>
               <DEPENDVALUE><![CDATA[]]></DEPENDVALUE>
          </ITEM>
          <ITEM TYPE="multichoice" REQUIRED="0">
               <ITEMID><![CDATA[1005]]></ITEMID>
               <ITEMTEXT><![CDATA[2. 問題解決]]></ITEMTEXT>
               <ITEMLABEL><![CDATA[22221203-2]]></ITEMLABEL>
               <PRESENTATION><![CDATA[r>>>>>A|B|C|D|E|X<<<<<1]]></PRESENTATION>
               <OPTIONS><![CDATA[h]]></OPTIONS>
               <DEPENDITEM><![CDATA[0]]></DEPENDITEM>
               <DEPENDVALUE><![CDATA[]]></DEPENDVALUE>
          </ITEM>
          <ITEM TYPE="multichoice" REQUIRED="0">
               <ITEMID><![CDATA[1006]]></ITEMID>
               <ITEMTEXT><![CDATA[3. コミュニケーション能力]]></ITEMTEXT>
               <ITEMLABEL><![CDATA[22221203-3]]></ITEMLABEL>
               <PRESENTATION><![CDATA[r>>>>>A|B|C|D|E|X<<<<<1]]></PRESENTATION>
               <OPTIONS><![CDATA[h]]></OPTIONS>
               <DEPENDITEM><![CDATA[0]]></DEPENDITEM>
               <DEPENDVALUE><![CDATA[]]></DEPENDVALUE>
          </ITEM>
          <ITEM TYPE="multichoice" REQUIRED="0">
               <ITEMID><![CDATA[1007]]></ITEMID>
               <ITEMTEXT><![CDATA[4. 論理的記述能力]]></ITEMTEXT>
               <ITEMLABEL><![CDATA[22221203-4]]></ITEMLABEL>
               <PRESENTATION><![CDATA[r>>>>>A|B|C|D|E|X<<<<<1]]></PRESENTATION>
               <OPTIONS><![CDATA[h]]></OPTIONS>
               <DEPENDITEM><![CDATA[0]]></DEPENDITEM>
               <DEPENDVALUE><![CDATA[]]></DEPENDVALUE>
          </ITEM>
          <ITEM TYPE="multichoice" REQUIRED="0">
               <ITEMID><![CDATA[1009]]></ITEMID>
               <ITEMTEXT><![CDATA[5. 継続的学習能力（指導教員のみ評価が有効）]]></ITEMTEXT>
               <ITEMLABEL><![CDATA[22221203-5]]></ITEMLABEL>
               <PRESENTATION><![CDATA[r>>>>>A|B|C|D|E|X<<<<<1]]></PRESENTATION>
               <OPTIONS><![CDATA[h]]></OPTIONS>
               <DEPENDITEM><![CDATA[1003]]></DEPENDITEM>
               <DEPENDVALUE><![CDATA[YES]]></DEPENDVALUE>
          </ITEM>
     </ITEMS>
</FEEDBACK>
